[
  {
    "name": "Aiham.net v2",
    "description": "My personal web page",
    "url": "http://www.aiham.net",
    "github": "https://github.com/aiham/Aiham.net-2",
    "tech": ["CSS", "HTML", "Javascript", "Angular"],
    "screenshots": ["/img/aihamnet2_1.png", "/img/aihamnet2_2.png", "/img/aihamnet2_3.png"]
  },
  {
    "name": "Reddit Scrubber",
    "description": "Automated deletion of a Reddit user's posts and/or comments",
    "url": "http://scrubber.aiham.net",
    "github": "https://github.com/aiham/RedditScrubber",
    "tech": ["HTML", "Javascript", "Node", "Express", "Sequelize", "MySQL", "Reddit API", "Foundation"],
    "screenshots": ["/img/scrubber_1.png", "/img/scrubber_2.png", "/img/scrubber_3.png"]
  },
  {
    "name": "Hidden City (iOS/Android)",
    "description": "Find new places to visit around your city via public transport with live updates",
    "honour": "Transport for NSW App Hot House 2012-13 Finalists",
    "tech": ["iPhone", "Android", "Haxe", "NME", "Python", "Django", "GTFS", "Open Street Maps"],
    "screenshots": ["/img/hiddencityapp_1.png", "/img/hiddencityapp_2.png", "/img/hiddencityapp_3.png"]
  },
  {
    "name": "Hidden City Website",
    "description": "Landing page for Hidden City mobile app",
    "url": "http://hiddencity.smallpotion.com",
    "tech": ["HTML", "Javascript", "CSS"],
    "screenshots": ["/img/hiddencitysite_1.png", "/img/hiddencitysite_2.png", "/img/hiddencitysite_3.png"]
  },
  {
    "name": "Gobble em Up (iOS)",
    "description": "Action mobile game. Fly around the screen while dodging the monsters",
    "honour": "Small Potion's first project",
    "tech": ["iPhone", "Objective-C", "Cocos-2D", "Accelerometer"],
    "screenshots": ["/img/gobble_1.png", "/img/gobble_2.png", "/img/gobble_3.png"]
  },
  {
    "name": "UTS Housing App (Hybrid iOS/Android)",
    "description": "App for tenants to create/update building maintenance tickets",
    "honour": "High Distinction mark for university project. Team leader of group of 10 students",
    "tech": ["HTML", "Javascript", "CSS", "Backbone", "jQuery Mobile", "Python", "Django", "MySQL", "Cordova"],
    "screenshots": ["/img/sdp_1.png", "/img/sdp_2.png", "/img/sdp_3.png"]
  },
  {
    "name": "Aiham.net v1",
    "description": "My personal web page",
    "github": "https://github.com/aiham/Aiham.net",
    "tech": ["HTML", "Javascript", "CSS", "PHP"],
    "screenshots": ["/img/aihamnet1_1.png", "/img/aihamnet1_2.png", "/img/aihamnet1_3.png"]
  },
  {
    "name": "Dymaxion Puzzle",
    "description": "Jigsaw puzzle game using photos of Japan",
    "honour": "Google HTML5 Open Call 2011 Finalist. Invited to Google Developer Day Tokyo",
    "url": "http://apps.aiham.net/dymaxion",
    "github": "https://github.com/aiham/dymaxion",
    "tech": ["Javascript", "Canvas", "Gyudon.js"],
    "screenshots": ["/img/dymaxion_1.png", "/img/dymaxion_2.png", "/img/dymaxion_3.png"]
  },
  {
    "name": "Chizuatter (iOS)",
    "description": "View your favourite Google My Maps on your iPhone",
    "url": "https://itunes.apple.com/au/app/chizuatter-for-iphone/id354990436",
    "tech": ["iPhone", "Objective-C", "Google Maps"],
    "screenshots": ["/img/chizuatter_ios_1.png", "/img/chizuatter_ios_2.png", "/img/chizuatter_ios_3.png"]
  },
  {
    "name": "Chizuatter (Android)",
    "description": "View your favourite Google My Maps on your Android phone",
    "honour": "Angency's first Android app",
    "url": "https://play.google.com/store/apps/details?id=com.p1d.chizuatter",
    "tech": ["Android", "Java", "Google Maps"],
    "screenshots": ["/img/chizuatter_android_1.png", "/img/chizuatter_android_2.png", "/img/chizuatter_android_3.png"]
  },
  {
    "name": "Okaeri Favorites",
    "description": "Twitter Bot that periodically reminds you of your favourite tweets",
    "url": "http://okafav.p1dlab.com",
    "tech": ["HTML", "Javascript", "CSS", "PHP", "MySQL", "Twitter API"],
    "screenshots": ["/img/okafav_1.png", "/img/okafav_2.png", "/img/okafav_3.png"]
  },
  {
    "name": "Friend World Clock",
    "description": "See at a glance what time it is for your friends around the world",
    "url": "https://www.p1dlab.com/fb/worldclock/",
    "tech": ["Javascript", "Canvas", "Gyudon.js", "PHP", "Facebook API"],
    "screenshots": ["/img/worldclock_1.png", "/img/worldclock_2.png", "/img/worldclock_3.png"]
  },
  {
    "name": "Aiham's Mayhem",
    "description": "Personal blog, forum and image gallery with admin panel",
    "honour": "My first CMS built from scratch",
    "url": "http://www.aihamsmayhem.com",
    "tech": ["HTML", "CSS", "PHP", "MySQL"],
    "screenshots": ["/img/aihamsmayhem_1.png", "/img/aihamsmayhem_2.png", "/img/aihamsmayhem_3.png"]
  }
]
